{
  "users": [
    {
      "id": 1,
      "name": "John",
      "surname": "Doe",
      "dateOfBirth": "1990-05-15",
      "position": "Developer",
      "online": true,
      "country": "USA"
    },
    {
      "id": 2,
      "name": "Jane",
      "surname": "Smith",
      "dateOfBirth": "1985-08-22",
      "position": "Project Manager",
      "online": false,
      "country": "Canada"
    },
    {
      "id": 3,
      "name": "Alex",
      "surname": "Johnson",
      "dateOfBirth": "1995-12-10",
      "position": "Trainee",
      "online": true,
      "country": "UK"
    },
    {
      "id": 4,
      "name": "Eva",
      "surname": "Brown",
      "dateOfBirth": "1992-03-25",
      "position": "Junior Developer",
      "online": true,
      "country": "Germany"
    },
    {
      "id": 5,
      "name": "Michael",
      "surname": "Miller",
      "dateOfBirth": "1988-07-08",
      "position": "Senior Developer",
      "online": false,
      "country": "Australia"
    },
    {
      "id": 6,
      "name": "Sophia",
      "surname": "Williams",
      "dateOfBirth": "1993-09-20",
      "position": "UX Designer",
      "online": true,
      "country": "France"
    },
    {
      "id": 7,
      "name": "Daniel",
      "surname": "Johnson",
      "dateOfBirth": "1986-01-12",
      "position": "Tech Lead",
      "online": false,
      "country": "Sweden"
    },
    {
      "id": 8,
      "name": "Olivia",
      "surname": "White",
      "dateOfBirth": "1991-04-30",
      "position": "QA Tester",
      "online": true,
      "country": "Spain"
    },
    {
      "id": 9,
      "name": "William",
      "surname": "Davis",
      "dateOfBirth": "1984-11-05",
      "position": "Product Manager",
      "online": false,
      "country": "Brazil"
    },
    {
      "id": 10,
      "name": "Emma",
      "surname": "Anderson",
      "dateOfBirth": "1994-06-18",
      "position": "Intern",
      "online": true,
      "country": "Netherlands"
    },
    {
      "id": 11,
      "name": "Liam",
      "surname": "Jones",
      "dateOfBirth": "1987-02-28",
      "position": "DevOps Engineer",
      "online": true,
      "country": "India"
    },
    {
      "name": "Alyssa",
      "surname": "Tompson",
      "dateOfBirth": "2001-06-06",
      "position": "Java Developer",
      "country": "Spain",
      "id": 12
    },
    {
      "name": "dadad",
      "surname": "adadad",
      "dateOfBirth": "2009-12-15",
      "position": "dadad",
      "country": "adadad",
      "id": 13
    },
    {
      "name": "dsd",
      "surname": "sd",
      "dateOfBirth": "2009-11-30",
      "position": "sdsd",
      "country": "sdsd",
      "id": 14
    },
    {
      "name": "essd",
      "surname": "sdsdsd",
      "dateOfBirth": "2009-12-01",
      "position": "sdsds",
      "country": "dsdsds",
      "id": 15
    },
    {
      "name": "ddfd",
      "surname": "dfdf",
      "dateOfBirth": "2009-12-03",
      "position": "dfdf",
      "country": "fdfdf",
      "id": 16
    },
    {
      "name": "qqq",
      "surname": "qqq",
      "dateOfBirth": "2009-12-02",
      "position": "qqqq",
      "country": "qqqqq",
      "id": 17
    },
    {
      "name": "sfsf",
      "surname": "sfs",
      "dateOfBirth": "2009-11-30",
      "position": "ssff",
      "country": "sfsf",
      "id": 18
    },
    {
      "name": "fssf",
      "surname": "fsf",
      "dateOfBirth": "2009-12-02",
      "position": "sfsf",
      "country": "sfs",
      "id": 19
    },
    {
      "name": "dda",
      "surname": "dad",
      "dateOfBirth": "2009-12-02",
      "position": "adda",
      "country": "dada",
      "id": 20
    }
  ]
}